trytond/modules/cashbook_dataexchange/README.rst
trytond/modules/cashbook_dataexchange/__init__.py
trytond/modules/cashbook_dataexchange/book.py
trytond/modules/cashbook_dataexchange/category.py
trytond/modules/cashbook_dataexchange/message.xml
trytond/modules/cashbook_dataexchange/qif_export.py
trytond/modules/cashbook_dataexchange/qif_export.xml
trytond/modules/cashbook_dataexchange/qif_import_wiz.py
trytond/modules/cashbook_dataexchange/qif_import_wiz.xml
trytond/modules/cashbook_dataexchange/qiftool.py
trytond/modules/cashbook_dataexchange/tryton.cfg
trytond/modules/cashbook_dataexchange/versiondep.txt
trytond/modules/cashbook_dataexchange/locale/de.po
trytond/modules/cashbook_dataexchange/locale/en.po
trytond/modules/cashbook_dataexchange/report/exort.fods
trytond/modules/cashbook_dataexchange/tests/__init__.py
trytond/modules/cashbook_dataexchange/tests/category.py
trytond/modules/cashbook_dataexchange/tests/party.py
trytond/modules/cashbook_dataexchange/tests/qifdata.py
trytond/modules/cashbook_dataexchange/tests/test_module.py
trytond/modules/cashbook_dataexchange/tests/transaction.py
trytond/modules/cashbook_dataexchange/view/wiz_qifimport_info_form.xml
trytond/modules/cashbook_dataexchange/view/wiz_qifimport_start_form.xml
mds_cashbook_dataexchange-7.0.5.dist-info/METADATA
mds_cashbook_dataexchange-7.0.5.dist-info/WHEEL
mds_cashbook_dataexchange-7.0.5.dist-info/entry_points.txt
mds_cashbook_dataexchange-7.0.5.dist-info/top_level.txt
mds_cashbook_dataexchange-7.0.5.dist-info/RECORD
